dynprogstorage/Wrapper_dynprogstorage.cpython-38-darwin.so
dynprogstorage/__init__.py
dynprogstorage/wrappers.py
dynprogstorage/tests/__init__.py
dynprogstorage/tests/test_current.py
dynprogstorage/tests/test_pycpl_function.py
dynprogstorage/tests/test_wrapper.py
dynprogstorage-0.1.10.dist-info/LICENSE
dynprogstorage-0.1.10.dist-info/METADATA
dynprogstorage-0.1.10.dist-info/WHEEL
dynprogstorage-0.1.10.dist-info/top_level.txt
dynprogstorage-0.1.10.dist-info/RECORD
