Metadata-Version: 2.1
Name: dynprogstorage
Version: 0.1.10
Summary: UNKNOWN
Home-page: https://github.com/robingirard/dynprogstorage
Author: Robin Girard
Author-email: robin.girard@mines-paristech.fr
License: Type license() to see the full license text
Project-URL: Code, https://github.com/robingirard/dynprogstorage
Platform: UNKNOWN
Classifier: Development Status :: 1 - Planning
Classifier: License :: OSI Approved :: MIT License
Classifier: Intended Audience :: Education
Classifier: Intended Audience :: Science/Research
Classifier: Topic :: Scientific/Engineering
Classifier: Topic :: Scientific/Engineering :: Mathematics
Classifier: Natural Language :: English
Classifier: Operating System :: OS Independent
Classifier: Programming Language :: C
Classifier: Programming Language :: Cython
Classifier: Programming Language :: Python
Classifier: Programming Language :: Python :: 3
Classifier: Programming Language :: Python :: 3.8
Classifier: Programming Language :: Python :: 3 :: Only
Classifier: Programming Language :: Python :: Implementation :: CPython
Requires-Python: >=3.8
